cppmath/__init__.py
cppmath/cache.py
cppmath/core.py
cppmath/integration.py
cppmath/linear.py
cppmath/optimization.py
cppmath/utils.py
cppmath copy/__init__.py
cppmath copy/cache.py
cppmath copy/core.py
cppmath copy/integration.py
cppmath copy/linear.py
cppmath copy/optimization.py
cppmath copy/utils.py
cppmath-1.0.5.dist-info/LICENSE
cppmath-1.0.5.dist-info/METADATA
cppmath-1.0.5.dist-info/WHEEL
cppmath-1.0.5.dist-info/top_level.txt
cppmath-1.0.5.dist-info/RECORD
